LICENSE
MANIFEST.in
README.md
requirements.txt
setup.py
mantiumapi/__init__.py
mantiumapi/ai_engines.py
mantiumapi/ai_methods.py
mantiumapi/apikey.py
mantiumapi/client.py
mantiumapi/engine_id_values.py
mantiumapi/execute.py
mantiumapi/files.py
mantiumapi/intelet.py
mantiumapi/log.py
mantiumapi/prompt.py
mantiumapi/security.py
mantiumapi/tag.py
mantiumapi/version.py
mantiumapi.egg-info/PKG-INFO
mantiumapi.egg-info/SOURCES.txt
mantiumapi.egg-info/dependency_links.txt
mantiumapi.egg-info/not-zip-safe
mantiumapi.egg-info/requires.txt
mantiumapi.egg-info/top_level.txt
tests/__init__.py
tests/test_ai_engines.py
tests/test_ai_method.py
tests/test_apikey.py
tests/test_auth.py
tests/test_files.py
tests/test_intelet.py
tests/test_log.py
tests/test_prompt.py